simpy_playground/__init__.py
simpy_playground/__main__.py
simpy_playground/_version.py
simpy_playground/version.py
simpy_playground-0.1.0a2.dist-info/METADATA
simpy_playground-0.1.0a2.dist-info/WHEEL
simpy_playground-0.1.0a2.dist-info/entry_points.txt
simpy_playground-0.1.0a2.dist-info/RECORD
